app_demo222/__init__.py
app_demo222/api.py
app_demo222/doc.py
app_demo222/field.py
app_demo222/model.py
app_demo222/schema.py
fastapi_builder/__init__.py
fastapi_builder/__main__.py
fastapi_builder/config.py
fastapi_builder/constants.py
fastapi_builder/context.py
fastapi_builder/generator.py
fastapi_builder/helpers.py
fastapi_builder/main.py
fastapi_builder/utils.py
fastapi_builder/templates/__init__.py
fastapi_builder/templates/app/__init__.py
fastapi_builder/templates/app/cookiecutter.json
fastapi_builder/templates/app/app_{{ cookiecutter.folder_name }}/__init__.py
fastapi_builder/templates/app/app_{{ cookiecutter.folder_name }}/api.py
fastapi_builder/templates/app/app_{{ cookiecutter.folder_name }}/doc.py
fastapi_builder/templates/app/app_{{ cookiecutter.folder_name }}/field.py
fastapi_builder/templates/app/app_{{ cookiecutter.folder_name }}/model.py
fastapi_builder/templates/app/app_{{ cookiecutter.folder_name }}/schema.py
fastapi_builder/templates/app/hooks/__init__.py
fastapi_builder/templates/app/hooks/post_gen_app.py
fastapi_builder/templates/project/__init__.py
fastapi_builder/templates/project/cookiecutter.json
fastapi_builder/templates/project/hooks/__init__.py
fastapi_builder/templates/project/hooks/post_gen_project.py
fastapi_builder/templates/project/{{ cookiecutter.folder_name }}/.flake8
fastapi_builder/templates/project/{{ cookiecutter.folder_name }}/.pre-commit-config.yaml
fastapi_builder/templates/project/{{ cookiecutter.folder_name }}/Dockerfile
fastapi_builder/templates/project/{{ cookiecutter.folder_name }}/LICENSE
fastapi_builder/templates/project/{{ cookiecutter.folder_name }}/README.md
fastapi_builder/templates/project/{{ cookiecutter.folder_name }}/README_EN.md
fastapi_builder/templates/project/{{ cookiecutter.folder_name }}/__init__.py
fastapi_builder/templates/project/{{ cookiecutter.folder_name }}/alembic.ini
fastapi_builder/templates/project/{{ cookiecutter.folder_name }}/docker-compose.yaml
fastapi_builder-2.0.0.dist-info/LICENSE
fastapi_builder-2.0.0.dist-info/METADATA
fastapi_builder-2.0.0.dist-info/WHEEL
fastapi_builder-2.0.0.dist-info/entry_points.txt
fastapi_builder-2.0.0.dist-info/top_level.txt
fastapi_builder-2.0.0.dist-info/RECORD
