Metadata-Version: 2.1
Name: fastapi-builder
Version: 2.0.0
Summary: fastapi-builder Project generator and manager for FastAPI
Home-page: https://github.com/fmw666/fastapi-builder
Author: fmw666
Author-email: fmw19990718@gmail.com
License: https://mit-license.org/
Keywords: fastapi,builder,project,python,fastapi-builder
Classifier: Development Status :: 3 - Alpha
Classifier: Intended Audience :: Developers
Classifier: Topic :: Software Development :: Build Tools
Classifier: License :: OSI Approved :: MIT License
Classifier: Programming Language :: Python :: 3
Classifier: Programming Language :: Python :: 3.8
Classifier: Programming Language :: Python :: 3.9
Classifier: Programming Language :: Python :: 3.10
Classifier: Programming Language :: Python :: 3.11
Classifier: Programming Language :: Python :: 3.12
Classifier: Programming Language :: Python :: Implementation :: CPython
Classifier: Operating System :: OS Independent
License-File: LICENSE
Requires-Dist: click (==8.0.3)
Requires-Dist: cookiecutter (==1.7.3)
Requires-Dist: email-validator (==1.1.3)
Requires-Dist: pydantic (==1.8.2)
Requires-Dist: pymysql (==1.0.2)
Requires-Dist: questionary (==1.10.0)
Requires-Dist: typer (==0.4.0)
